LICENSE
README.md
install.json
jupyterlab_cell_lock/__init__.py
jupyterlab_cell_lock/_version.py
jupyterlab_cell_lock/labextension/package.json
jupyterlab_cell_lock/labextension/static/420.5f065c24107f5475a531.js
jupyterlab_cell_lock/labextension/static/728.bae7f9c8600f52be6138.js
jupyterlab_cell_lock/labextension/static/remoteEntry.944211ad06aa66bb2603.js
jupyterlab_cell_lock/labextension/static/style.js
jupyterlab_cell_lock/labextension/static/third-party-licenses.json
package.json
pyproject.toml
src/icon.ts
src/index.ts
src/metadata.ts
src/status.ts
style/base.css
style/index.css
style/index.js
tsconfig.json
yarn.lock
jupyterlab_cell_lock-0.3.2.data/data/share/jupyter/labextensions/jupyterlab-cell-lock/package.json
jupyterlab_cell_lock-0.3.2.data/data/share/jupyter/labextensions/jupyterlab-cell-lock/static/420.5f065c24107f5475a531.js
jupyterlab_cell_lock-0.3.2.data/data/share/jupyter/labextensions/jupyterlab-cell-lock/static/728.bae7f9c8600f52be6138.js
jupyterlab_cell_lock-0.3.2.data/data/share/jupyter/labextensions/jupyterlab-cell-lock/static/remoteEntry.944211ad06aa66bb2603.js
jupyterlab_cell_lock-0.3.2.data/data/share/jupyter/labextensions/jupyterlab-cell-lock/static/style.js
jupyterlab_cell_lock-0.3.2.data/data/share/jupyter/labextensions/jupyterlab-cell-lock/static/third-party-licenses.json
jupyterlab_cell_lock-0.3.2.data/data/share/jupyter/labextensions/jupyterlab-cell-lock/commands/install.json
jupyterlab_cell_lock-0.3.2.dist-info/METADATA
jupyterlab_cell_lock-0.3.2.dist-info/WHEEL
jupyterlab_cell_lock-0.3.2.dist-info/licenses/LICENSE
jupyterlab_cell_lock-0.3.2.dist-info/RECORD
