Metadata-Version: 2.4
Name: jupyterlab-cell-lock
Version: 0.3.2
Summary: JupyterLab extension for easily locking cells, making them read-only and undeletable.
Project-URL: Homepage, https://github.com/jrdnbradford/jupyterlab-cell-lock
Project-URL: Bug Tracker, https://github.com/jrdnbradford/jupyterlab-cell-lock/issues
Project-URL: Repository, https://github.com/jrdnbradford/jupyterlab-cell-lock.git
Author: Jordan Bradford
License: BSD 3-Clause License
License-File: LICENSE
Keywords: jupyter,jupyterlab,jupyterlab-extension
Classifier: Framework :: Jupyter
Classifier: Framework :: Jupyter :: JupyterLab
Classifier: Framework :: Jupyter :: JupyterLab :: 4
Classifier: Framework :: Jupyter :: JupyterLab :: Extensions
Classifier: Framework :: Jupyter :: JupyterLab :: Extensions :: Prebuilt
Classifier: License :: OSI Approved :: BSD License
Classifier: Programming Language :: Python
Classifier: Programming Language :: Python :: 3
Classifier: Programming Language :: Python :: 3.9
Classifier: Programming Language :: Python :: 3.10
Classifier: Programming Language :: Python :: 3.11
Classifier: Programming Language :: Python :: 3.12
Classifier: Programming Language :: Python :: 3.13
Requires-Python: >=3.9
